{
  "title": "MSC Cruises Adriatic Cruises 2026",
  "intro": "MSC Cruises, the world's largest privately-owned cruise line, brings its signature Mediterranean flair to the stunning Adriatic Sea. Operating from its ancestral Italian roots, MSC offers immersive itineraries through one of Europe's most historically rich and visually dramatic coastlines. Sail aboard modern, elegantly designed ships featuring European-style service, authentic Italian cuisine, and international entertainment. The Adriatic region showcases MSC's strengths: proximity to home ports, competitive pricing, and deep cultural connections to destinations like Croatia, Montenegro, and Slovenia. With multilingual crews and a cosmopolitan atmosphere, MSC attracts European and international travelers seeking value without sacrificing style. Their Adriatic cruises combine UNESCO World Heritage sites, crystal-clear waters, and medieval walled cities with the line's renowned family-friendly amenities, including partnerships with LEGO and Chicco. Whether exploring Dubrovnik's limestone streets or Venice's canals, MSC delivers an authentic European cruise experience at accessible price points.",
  "quick_facts": {
    "price_from_eur": 549,
    "duration_range": "7-14 nights",
    "best_months": [
      "May",
      "Jun",
      "Sep",
      "Oct"
    ],
    "ships_on_route": [
      "MSC World Europa",
      "MSC Seaview",
      "MSC Seaside",
      "MSC Orchestra",
      "MSC Sinfonia"
    ],
    "departure_ports": [
      "Venice",
      "Bari",
      "Trieste",
      "Genoa",
      "Barcelona"
    ]
  },
  "price_by_season": [
    {
      "season": "Shoulder (Mar-Apr, Nov)",
      "inside_eur": 549,
      "balcony_eur": 799,
      "suite_eur": 1299
    },
    {
      "season": "Peak (May-Jun, Sep-Oct)",
      "inside_eur": 699,
      "balcony_eur": 999,
      "suite_eur": 1599
    },
    {
      "season": "High Summer (Jul-Aug)",
      "inside_eur": 899,
      "balcony_eur": 1299,
      "suite_eur": 1999
    }
  ],
  "sample_itineraries": [
    {
      "name": "7-night Adriatic & Greece",
      "duration_nights": 7,
      "ports": [
        "Venice",
        "Bari",
        "Corfu",
        "Santorini",
        "Mykonos",
        "Dubrovnik",
        "Venice"
      ],
      "price_from_eur": 599,
      "highlight": "Iconic Greek islands combined with Croatian coast"
    },
    {
      "name": "7-night Western Mediterranean & Adriatic",
      "duration_nights": 7,
      "ports": [
        "Genoa",
        "Naples",
        "Messina",
        "Corfu",
        "Dubrovnik",
        "Venice"
      ],
      "price_from_eur": 549,
      "highlight": "Italian heritage cities to Dalmatian coast"
    },
    {
      "name": "14-night Grand Mediterranean",
      "duration_nights": 14,
      "ports": [
        "Barcelona",
        "Marseille",
        "Genoa",
        "Naples",
        "Sicily",
        "Malta",
        "Corfu",
        "Dubrovnik",
        "Split",
        "Venice",
        "Bari",
        "Katakolon",
        "Santorini",
        "Mykonos",
        "Barcelona"
      ],
      "price_from_eur": 1099,
      "highlight": "Comprehensive Mediterranean and Adriatic immersion"
    }
  ],
  "ships_detail": [
    {
      "name": "MSC World Europa",
      "capacity": 6762,
      "year": 2022,
      "best_for": "Families & Modern Luxury Seekers",
      "price_from_eur": 799
    },
    {
      "name": "MSC Seaview",
      "capacity": 5179,
      "year": 2018,
      "best_for": "Outdoor Enthusiasts & Sea Views",
      "price_from_eur": 649
    },
    {
      "name": "MSC Seaside",
      "capacity": 5179,
      "year": 2017,
      "best_for": "Caribbean-style cruising in Europe",
      "price_from_eur": 599
    },
    {
      "name": "MSC Orchestra",
      "capacity": 2550,
      "year": 2007,
      "best_for": "Traditional cruisers & Value seekers",
      "price_from_eur": 499
    },
    {
      "name": "MSC Sinfonia",
      "capacity": 2680,
      "year": 2005,
      "best_for": "Intimate ship experience & Budget travelers",
      "price_from_eur": 549
    }
  ],
  "whats_included": [
    "Accommodation in chosen cabin category",
    "All meals in main dining room and buffet",
    "Entertainment shows and live music",
    "Fitness center and pool access",
    "Kids clubs and family activities",
    "Port taxes and basic service charges"
  ],
  "whats_extra": [
    "Beverage packages (from €35/day)",
    "Specialty dining (€25-45/person)",
    "Shore excursions (€45-189)",
    "Spa treatments and salon services",
    "WiFi packages (€12-30/day)",
    "Gratuities (€12/adult/day recommended)",
    "Laundry and dry cleaning",
    "Casino and shopping"
  ],
  "booking_strategy": "Book 8-12 months ahead for best cabin selection and early booking discounts up to 30%. MSC's 'Bella' experience offers lowest rates while 'Fantastica' and 'Aurea' packages include priority boarding, cabin upgrades, and drink packages. Consider repositioning cruises in April and November for exceptional value. MSC Voyagers Club members receive additional 5% loyalty discount plus status match from other cruise lines. Wave season (January-March) features promotional rates with reduced deposits.",
  "top_ports": [
    {
      "port": "Dubrovnik, Croatia",
      "time_in_port": "7am-7pm",
      "top_activity": "City Walls Walk & Cable Car (€35)",
      "tip": "Arrive early at Pile Gate to avoid cruise crowds; book cable car online"
    },
    {
      "port": "Split, Croatia",
      "time_in_port": "8am-6pm",
      "top_activity": "Diocletian's Palace & Trogir (€55)",
      "tip": "Explore the palace's living quarters within the ancient walls"
    },
    {
      "port": "Kotor, Montenegro",
      "time_in_port": "8am-5pm",
      "top_activity": "Fortress Hike & Boat to Our Lady of the Rocks (€45)",
      "tip": "Start fortress climb by 8:30am before heat and crowds"
    },
    {
      "port": "Venice, Italy",
      "time_in_port": "Varies (overnight possible)",
      "top_activity": "St. Mark's Basilica & Doge's Palace (€65)",
      "tip": "Pre-book timed entry tickets; cruise ships dock at Marghera or San Basilio"
    },
    {
      "port": "Corfu, Greece",
      "time_in_port": "8am-4pm",
      "top_activity": "Achilleion Palace & Paleokastritsa (€55)",
      "tip": "Short port time prioritizes organized excursions over independent exploration"
    },
    {
      "port": "Bari, Italy",
      "time_in_port": "8am-6pm",
      "top_activity": "Alberobello Trulli & Matera Sassi (€75)",
      "tip": "UNESCO sites require 45+ minute drive; ship excursions recommended"
    }
  ],
  "faqs": [
    {
      "question": "How much does a MSC Cruises Adriatic cruise cost?",
      "answer": "MSC Adriatic cruises start from €549 per person for interior cabins on 7-night itineraries during shoulder seasons (March-April, November). Peak season (May-June, September-October) typically ranges €699-999 for balcony cabins. High summer (July-August) commands premium pricing from €899-1299. Suite accommodations range €1299-1999 depending on season. Prices exclude gratuities (€12/adult/day), beverage packages, and shore excursions. MSC frequently offers promotions including kids sail free, reduced deposits, and onboard credit. The 'Bella' experience provides lowest rates while 'Fantastica' and 'Aurea' packages add value through cabin upgrades and inclusive amenities. Repositioning cruises and last-minute deals occasionally drop below €499."
    },
    {
      "question": "Which MSC Cruises ships sail to Adriatic?",
      "answer": "MSC deploys multiple ships to Adriatic routes depending on season. MSC World Europa, the line's newest LNG-powered flagship, offers the most innovative experience with 6762 passengers. MSC Seaview and MSC Seaside provide outdoor-focused cruising with extensive pool decks and sea-view elevators. These larger resort-style ships dominate summer deployments. Smaller, more traditional vessels including MSC Orchestra and MSC Sinfonia offer intimate experiences with 2500-2680 passengers, often at lower price points during shoulder seasons. Ship assignments rotate annually based on deployment schedules, with Venice, Bari, and Trieste serving as primary homeports. Winter 2026 sees reduced Adriatic presence as ships reposition to Caribbean and Arabian Gulf."
    },
    {
      "question": "When is best time to cruise Adriatic?",
      "answer": "The optimal Adriatic cruising window spans May through October, with peak experiences in late May-June and September-early October. These months deliver ideal conditions: warm temperatures (22-28°C), calm seas, minimal rainfall, and manageable crowds. July-August brings hottest weather (30-35°C) and peak tourist congestion at UNESCO sites like Dubrovnik's walls, though sea temperatures perfect for swimming. September offers exceptional value with warm water, harvest season cuisine, and reduced cruise traffic. May provides wildflower-covered hillsides and lower prices before summer escalation. November-March sailings are limited and weather-unpredictable, with many attractions closed or operating reduced hours. Croatian coastal destinations particularly shine in autumn when cruise ship numbers decrease significantly."
    },
    {
      "question": "What is included?",
      "answer": "MSC's base fare includes accommodation, all main dining room and buffet meals, standard entertainment including theater shows and live music, fitness center access, swimming pools, and supervised kids clubs for ages 3-17. Port taxes and basic service charges are included at booking. What's notably excluded: beverages beyond water, coffee, and tea at meals; specialty restaurants; shore excursions; WiFi; spa services; and gratuities (recommended €12/adult/day). MSC structures experiences hierarchically: 'Bella' (basic), 'Fantastica' (priority boarding, cabin choice, 20% dining discount), and 'Aurea' (premium drinks package, spa access, anytime dining). Unlike premium competitors, MSC positions itself as à-la-carte cruising where base rates attract, while onboard spending drives profitability."
    },
    {
      "question": "Which ports?",
      "answer": "MSC Adriatic itineraries feature an exceptional concentration of UNESCO World Heritage sites. Croatian highlights include Dubrovnik's complete walled old town, Split's living Roman palace of Diocletian, and charming Zadar with its sea organ. Montenegro's Bay of Kotor delivers dramatic fjord-like scenery with medieval fortified towns. Italian departure ports Venice, Bari, and Trieste each offer distinct regional character—Venice's canal labyrinth, Bari's authentic Puglia access, Trieste's Habsburg elegance. Greek island calls typically include Corfu's Venetian architecture. Extended itineraries reach Slovenia's Ljubljana, Albania's emerging Saranda, and Montenegro's Budva. Most 7-night cruises include 3-4 Adriatic ports with sea days limited, maximizing destination immersion while maintaining reasonable pacing for active exploration."
    },
    {
      "question": "How far ahead to book?",
      "answer": "For optimal MSC Adriatic cruises, book 8-12 months in advance, particularly for summer 2026 sailings and balcony cabins on newer ships like MSC World Europa. Early booking typically secures 20-30% discounts, cabin location preference, and promotional perks including onboard credit or beverage packages. Venice departures require particular advance planning due to ongoing port capacity restrictions and regulatory uncertainty. Families seeking connecting cabins or specific configurations should prioritize early reservations. Wave season (January-March) brings aggressive MSC promotions with reduced deposits (often €50-100 versus standard €250). Last-minute deals emerge 60-90 days before sailing for flexible travelers, though cabin selection becomes limited. Group bookings of 8+ cabins warrant 12-18 month advance planning for best rates and amenities."
    },
    {
      "question": "Good for families?",
      "answer": "MSC excels as a family-friendly Adriatic option with genuinely complimentary kids programming and competitive pricing for multi-occupancy cabins. The line's partnership with LEGO creates dedicated play areas and building competitions. Babies under 3 receive complimentary Chicco-equipped cabins and bottle warmers. Kids clubs divide ages 3-6, 7-11, 12-14, and 15-17 with supervised activities until midnight. Family cabins and connecting rooms accommodate larger groups efficiently. The multicultural environment exposes children to multiple languages and international peer interaction. However, families should note: dining runs on European schedules (late seatings), beverage packages don't include children, and shore excursions may lack kid-specific pricing. Pool decks become crowded on sea days. For families prioritizing destination education over shipboard waterparks, MSC's Adriatic itineraries deliver exceptional cultural exposure at moderate cost."
    },
    {
      "question": "Cancellation policy?",
      "answer": "MSC's cancellation policy operates on a tiered structure based on departure proximity. Cancellations 90+ days before sailing incur no penalty beyond administrative fees (typically €50-100). 89-61 days prior: deposit forfeiture (usually €250 per cabin). 60-46 days: 25% of total fare. 45-16 days: 50% of total fare. 15 days or less: 100% forfeiture. These terms apply to standard bookings; promotional rates may impose stricter non-refundable deposit requirements. MSC strongly recommends comprehensive travel insurance covering cancellation for medical reasons, which standard policies exclude. 'Cruise Care' protection purchased through MSC offers cancellation for any reason with future cruise credit minus administrative fee. COVID-19 protocols have stabilized but health-related cancellations now follow standard medical documentation requirements rather than automatic refunds. Always verify specific terms at booking confirmation."
    }
  ]
}