{
  "title": "P&O Cruises Northern Europe Cruises 2026",
  "intro": "P&O Cruises brings British elegance to Northern Europe's most captivating destinations, combining traditional maritime heritage with contemporary comfort. As the UK's premier cruise line, P&O offers immersive voyages through Norway's majestic fjords, the Baltic Sea's historic capitals, and Iceland's dramatic landscapes. Their ships provide a uniquely British experience—from afternoon tea to West End-style entertainment—while exploring destinations like St. Petersburg, Copenhagen, and the Norwegian coast. Whether you seek the midnight sun of summer or Northern Lights of autumn, P&O's Northern Europe itineraries balance cultural enrichment with relaxation. The line's understanding of British travellers ensures familiar comforts alongside extraordinary adventures, from dog sledding in Tromsø to exploring medieval Tallinn. With dedicated adult-only ships and family-friendly options, P&O crafts Northern European journeys that resonate with discerning passengers seeking authentic experiences delivered with understated sophistication.",
  "quick_facts": {
    "price_from_eur": 699,
    "duration_range": "7-14 nights",
    "best_months": [
      "May",
      "Jun",
      "Jul",
      "Aug",
      "Sep"
    ],
    "ships_on_route": [
      "Iona",
      "Arvia",
      "Britannia",
      "Azura",
      "Ventura"
    ],
    "departure_ports": [
      "Southampton",
      "Rotterdam"
    ]
  },
  "price_by_season": [
    {
      "season": "Shoulder (May, Sep)",
      "inside_eur": 699,
      "balcony_eur": 999,
      "suite_eur": 1599
    },
    {
      "season": "Peak (Jun-Aug)",
      "inside_eur": 899,
      "balcony_eur": 1299,
      "suite_eur": 1999
    },
    {
      "season": "Northern Lights (Oct-Nov)",
      "inside_eur": 799,
      "balcony_eur": 1149,
      "suite_eur": 1799
    }
  ],
  "sample_itineraries": [
    {
      "name": "7-night Norwegian Fjords",
      "duration_nights": 7,
      "ports": [
        "Southampton",
        "Stavanger",
        "Olden",
        "Hellesylt",
        "Geiranger",
        "Bergen",
        "Southampton"
      ],
      "price_from_eur": 699,
      "highlight": "Sail deep into UNESCO-listed Geirangerfjord with waterfall cruising"
    },
    {
      "name": "14-night Baltic Discovery",
      "duration_nights": 14,
      "ports": [
        "Southampton",
        "Copenhagen",
        "Tallinn",
        "St. Petersburg",
        "Helsinki",
        "Stockholm",
        "Warnemünde",
        "Southampton"
      ],
      "price_from_eur": 1299,
      "highlight": "Two full days in St. Petersburg with overnight stay"
    },
    {
      "name": "12-night Iceland & Norway",
      "duration_nights": 12,
      "ports": [
        "Southampton",
        "Bergen",
        "Ålesund",
        "Tórshavn",
        "Reykjavik",
        "Isafjordur",
        "Akureyri",
        "Southampton"
      ],
      "price_from_eur": 1149,
      "highlight": "Complete circumnavigation of Iceland with three Icelandic ports"
    }
  ],
  "ships_detail": [
    {
      "name": "Iona",
      "capacity": 5200,
      "year": 2021,
      "best_for": "Families & multi-generational groups",
      "price_from_eur": 749
    },
    {
      "name": "Arvia",
      "capacity": 5200,
      "year": 2022,
      "best_for": "Active families & Caribbean-style cruising",
      "price_from_eur": 799
    },
    {
      "name": "Britannia",
      "capacity": 3647,
      "year": 2015,
      "best_for": "Traditional British cruising with modern amenities",
      "price_from_eur": 699
    },
    {
      "name": "Azura",
      "capacity": 3100,
      "year": 2010,
      "best_for": "Adults seeking relaxed, destination-focused voyages",
      "price_from_eur": 649
    },
    {
      "name": "Ventura",
      "capacity": 3100,
      "year": 2008,
      "best_for": "Families with younger children",
      "price_from_eur": 649
    }
  ],
  "whats_included": [
    "Full board dining in main restaurants and buffet",
    "Afternoon tea service",
    "Evening entertainment and live shows",
    "Children's clubs and family activities",
    "Use of fitness centre and pools",
    "Port taxes and service charges",
    "Onboard currency in GBP"
  ],
  "whats_extra": [
    "Speciality restaurants (£15-28 per person)",
    "Drinks packages or à la carte beverages (£20-55 per day packages)",
    "Shore excursions (£45-180 per person)",
    "Spa treatments and salon services",
    "WiFi packages (£18-24 per day)",
    "Laundry services",
    "Casino gaming",
    "Photography services"
  ],
  "booking_strategy": "Book 9-12 months ahead for peak summer fjord and Baltic sailings, particularly for balcony cabins facing starboard (Norway) or port (Baltic) for optimal scenic views. Iona and Arvia's Northern Europe itineraries sell fastest due to newer amenities. Consider shoulder season (May or September) for 20-30% savings and fewer crowds at key ports. P&O frequently offers early booking incentives including free cabin upgrades and onboard credit. Solo travellers should book early as single cabins are limited. Watch for 'Select Price' fares offering cabin choice and flexibility versus 'Saver' fares for maximum value if cabin location matters less.",
  "top_ports": [
    {
      "port": "Geiranger, Norway",
      "time_in_port": "7am-4pm",
      "top_activity": "Dalsnibba Skywalk viewpoint excursion (€89)",
      "tip": "Book port-side cabin for fjord approach views"
    },
    {
      "port": "St. Petersburg, Russia",
      "time_in_port": "Overnight (2 days)",
      "top_activity": "Hermitage Museum guided tour (€145)",
      "tip": "Visa-free entry only via ship's organised tours—book early"
    },
    {
      "port": "Bergen, Norway",
      "time_in_port": "8am-5pm",
      "top_activity": "Flåm Railway to Myrdal (€95)",
      "tip": "Take funicular to Mount Fløyen independently for €15 if excursions sell out"
    },
    {
      "port": "Tallinn, Estonia",
      "time_in_port": "8am-5pm",
      "top_activity": "Medieval Old Town walking tour (€55)",
      "tip": "Walkable from port—save money exploring independently"
    },
    {
      "port": "Reykjavik, Iceland",
      "time_in_port": "7am-6pm",
      "top_activity": "Golden Circle tour (€165)",
      "tip": "Long excursion—ensure ship departure time allows full experience"
    },
    {
      "port": "Copenhagen, Denmark",
      "time_in_port": "8am-6pm",
      "top_activity": "Canal cruise and Tivoli Gardens (€75)",
      "tip": "Easy 20-minute walk to Nyhavn from cruise terminal"
    }
  ],
  "faqs": [
    {
      "question": "How much does a P&O Cruises Northern Europe cruise cost?",
      "answer": "P&O Cruises Northern Europe itineraries start from €699 for inside cabins on 7-night Norwegian Fjords sailings, rising to €899-1299 for peak summer departures. Balcony cabins typically range €999-1499, while suites command €1599-2499 depending on ship age and sailing date. The 14-night Baltic Discovery cruises start around €1299 inside, €1799 balcony. Shoulder season (May and September) offers 15-25% savings. Solo travellers pay 150-200% supplement unless booking dedicated single cabins. Drinks packages add €20-55 daily, while excursions average €60-120 per port. P&O's pricing includes service charges and port taxes, with onboard currency in GBP."
    },
    {
      "question": "Which P&O Cruises ships sail to Northern Europe?",
      "answer": "P&O deploys five ships on Northern Europe routes in 2026. Iona (2021) and Arvia (2022), the line's LNG-powered mega-ships, offer family-focused cruising with extensive entertainment. Britannia (2015) provides refined British elegance with celebrity chef partnerships. Azura and Ventura, though older, excel at destination-intensive itineraries with more port time. Iona and Arvia dominate summer Norwegian Fjords and Baltic sailings from Southampton, while Britannia offers select Iceland voyages. Azura handles extended Northern Lights itineraries October-November. All ships feature P&O's signature British touches—formal nights, afternoon tea, and curry menus—while differing in entertainment scale and dining variety."
    },
    {
      "question": "When is best time to cruise Northern Europe?",
      "answer": "June through August delivers the finest Northern Europe cruising weather, with temperatures 15-22°C, extended daylight hours (midnight sun above Arctic Circle), and optimal fjord visibility. July peak offers warmest conditions but highest prices and crowds. May and September provide 20-30% savings, fewer tourists, and excellent Northern Lights chances on late-September sailings. October-November dedicated Northern Lights itineraries operate with reduced daylight but spectacular aurora potential. Baltic cities shine May-September; St. Petersburg's White Nights (June) are magical. Iceland's summer offers puffin colonies and accessible highlands. For photography, September's autumn colours transform Norwegian landscapes dramatically."
    },
    {
      "question": "What is included?",
      "answer": "P&O Cruises includes comprehensive value: full board dining across main restaurants, buffet venues, and afternoon tea; all evening entertainment from West End-style productions to live music; children's clubs (ages 2-17); fitness centre and pool access; and port taxes. British passengers appreciate included service charges—no automatic gratuities. Speciality dining, beverages, WiFi, spa services, and shore excursions cost extra. Select Price fares include cabin choice, first-choice dining, and flexibility; Saver fares offer lower rates with assigned cabins. Unlike American lines, P&O doesn't push drinks packages aggressively. Currency onboard is GBP, simplifying budgeting for UK travellers. Room service incurs modest charges except for breakfast."
    },
    {
      "question": "Which ports?",
      "answer": "P&O's Northern Europe portfolio spans Norway's fjord region—Geiranger, Flåm, Ålesund, Stavanger, Bergen—where ships navigate UNESCO-listed waterways. Baltic itineraries feature St. Petersburg (overnight), Tallinn, Riga, Helsinki, Stockholm, Copenhagen, and Warnemünde for Berlin. Iceland routes include Reykjavik, Akureyri, Isafjordur, and Grundarfjordur. Arctic voyages reach Tromsø, Alta, and Honningsvåg near North Cape. British Isles exploration covers Scottish islands, Northern Ireland, and Republic of Ireland ports. Each itinerary balances iconic capitals with smaller, scenic harbours. Norwegian fjord sailings emphasise natural beauty with extended scenic cruising; Baltic voyages prioritise cultural immersion with longer port stays, particularly Russia's visa-free overnight access."
    },
    {
      "question": "How far ahead to book?",
      "answer": "Secure P&O Northern Europe cruises 9-12 months ahead for optimal choice, particularly for Iona and Arvia's popular summer itineraries. Balcony cabins with specific fjord-view positioning sell fastest—starboard for northbound Norway, port for southbound. School holiday departures (July, late October) require earliest booking. P&O releases itineraries approximately 18 months ahead, with best early booking incentives typically appearing 10-12 months out. Last-minute deals emerge 6-8 weeks before departure for flexible travellers, though cabin selection becomes limited. Solo travellers must book early as single cabins represent under 5% of inventory. Christmas market and Northern Lights sailings (November-December) often sell out by September."
    },
    {
      "question": "Good for families?",
      "answer": "P&O excels at multi-generational Northern Europe cruising. Iona and Arvia feature extensive family facilities: kids' clubs divided by age (2-4, 5-8, 9-12, 13-17), splash parks, climbing walls, and family-friendly entertainment. Ventura and Britannia offer strong children's programming with night nurseries for under-5s. Norwegian fjords particularly suit families—shorter flights from UK, no jet lag, dramatic scenery engaging all ages, and shore excursions like husky sledding and Viking experiences. Dining accommodates young palates with early children's tea service. Family cabins and interconnecting rooms book quickly. Adults-only ships Arcadia and Aurora never sail Northern Europe, ensuring family-appropriate atmosphere across the deployment. Onboard currency in GBP simplifies budgeting."
    },
    {
      "question": "Cancellation policy?",
      "answer": "P&O Cruises operates tiered cancellation penalties increasing closer to departure. Cancellations 90+ days before sailing incur deposit loss only (typically 15-20% of cruise fare). 89-60 days: 25% penalty; 59-42 days: 50%; 41-28 days: 75%; under 28 days: 100% forfeiture. 'Select Price' fares offer greater flexibility with reduced penalties versus non-refundable 'Saver' rates. P&O strongly recommends comprehensive travel insurance covering cruise-specific cancellation reasons. COVID-19 policies evolved to standard terms, though health protocols may apply. Name changes incur fees. For protected peace of mind, P&O's Cancellation Protection Plan (purchase at booking) allows cancellation for any reason with future cruise credit minus processing fee. Always verify specific terms at booking."
    }
  ]
}