{
  "title": "P&O Cruises Indian Ocean Cruises 2026",
  "intro": "P&O Cruises brings its distinctive British heritage to the Indian Ocean, offering sophisticated voyages from Southampton and fly-cruise options to this exotic region. As Britain's favourite cruise line since 1837, P&O combines traditional elegance with contemporary comfort for discerning travellers seeking winter sun escapes. Indian Ocean itineraries showcase the archipelagos of the Seychelles, Mauritius, and Réunion, alongside Sri Lankan cultural treasures and Maldivian atolls. The line's adults-only Arcadia and Aurora, plus family-friendly Azura and Ventura, provide tailored experiences whether you seek peaceful ocean vistas or multi-generational adventures. P&O's pound sterling onboard pricing, formal nights, and afternoon tea traditions create a uniquely British atmosphere. With extended port stays and overnight calls in Colombo and Port Louis, guests enjoy immersive exploration of spice markets, tea plantations, and UNESCO heritage sites across this mesmerising ocean basin.",
  "quick_facts": {
    "price_from_eur": 1899,
    "duration_range": "14-35 nights",
    "best_months": [
      "Nov",
      "Dec",
      "Jan",
      "Feb",
      "Mar"
    ],
    "ships_on_route": [
      "Arcadia",
      "Azura",
      "Aurora",
      "Ventura"
    ],
    "departure_ports": [
      "Southampton",
      "Valletta",
      "Dubai"
    ]
  },
  "price_by_season": [
    {
      "season": "Peak (Dec-Feb)",
      "inside_eur": 2199,
      "balcony_eur": 2899,
      "suite_eur": 4599
    },
    {
      "season": "Shoulder (Nov, Mar)",
      "inside_eur": 1899,
      "balcony_eur": 2499,
      "suite_eur": 3899
    },
    {
      "season": "Low (Apr-Oct limited)",
      "inside_eur": 1699,
      "balcony_eur": 2199,
      "suite_eur": 3299
    }
  ],
  "sample_itineraries": [
    {
      "name": "Seychelles & Indian Ocean Explorer",
      "duration_nights": 14,
      "ports": [
        "Valletta",
        "Suez Canal",
        "Aqaba",
        "Muscat",
        "Mumbai",
        "Colombo",
        "Malé"
      ],
      "price_from_eur": 1899,
      "highlight": "Iconic Suez Canal transit with Arabian and Indian subcontinent immersion"
    },
    {
      "name": "Mauritius, Réunion & South Africa",
      "duration_nights": 18,
      "ports": [
        "Cape Town",
        "Durban",
        "Port Louis",
        "Pointe des Galets",
        "Port Elizabeth"
      ],
      "price_from_eur": 2299,
      "highlight": "French colonial heritage and dramatic volcanic landscapes of Réunion"
    },
    {
      "name": "Grand Indian Ocean Adventure",
      "duration_nights": 35,
      "ports": [
        "Southampton",
        "Lisbon",
        "Funchal",
        "Barbados",
        "Grenada",
        "Cape Verde",
        "Cape Town",
        "Durban",
        "Port Louis",
        "Mumbai",
        "Dubai"
      ],
      "price_from_eur": 3499,
      "highlight": "Full world voyage segment with three oceans and comprehensive destination coverage"
    }
  ],
  "ships_detail": [
    {
      "name": "Arcadia",
      "capacity": 2096,
      "year": 2005,
      "best_for": "Adults seeking refined cruising",
      "price_from_eur": 1899
    },
    {
      "name": "Azura",
      "capacity": 3100,
      "year": 2010,
      "best_for": "Families and entertainment seekers",
      "price_from_eur": 1999
    },
    {
      "name": "Aurora",
      "capacity": 1870,
      "year": 2000,
      "best_for": "Traditional cruisers and world voyage enthusiasts",
      "price_from_eur": 1799
    },
    {
      "name": "Ventura",
      "capacity": 3092,
      "year": 2008,
      "best_for": "Active families with children",
      "price_from_eur": 1949
    }
  ],
  "whats_included": [
    "Full board dining in main restaurants and buffet",
    "Afternoon tea service",
    "Evening entertainment and live shows",
    "Use of fitness centre and swimming pools",
    "Children's clubs and family activities",
    "Port taxes and gratuities",
    "British currency onboard (no exchange fees)",
    "Lectures and enrichment programmes",
    "Deck games and library access"
  ],
  "whats_extra": [
    "Speciality dining restaurants (€25-45 per person)",
    "Drinks packages or à la carte beverages (€7-12 cocktails)",
    "Shore excursions (€45-189 per tour)",
    "Spa treatments and salon services",
    "WiFi packages (€15-25 per day)",
    "Laundry and dry cleaning",
    "Photography services",
    "Casino gaming",
    "Premium entertainment experiences"
  ],
  "booking_strategy": "Book 12-18 months ahead for best cabin selection and early booking discounts of up to 35%. P&O's Select Price offers cabin choice and benefits, while Saver Price provides lowest fares with assigned cabins. Watch for regional sales in January and September. Consider repositioning cruises in November and March for exceptional value. Loyalty club members receive priority access and additional discounts.",
  "top_ports": [
    {
      "port": "Port Louis, Mauritius",
      "time_in_port": "7am-6pm (often overnight)",
      "top_activity": "Pamplemousses Botanical Garden & sugar estate tour (€89)",
      "tip": "Negotiate taxi fares beforehand; explore central market for spices"
    },
    {
      "port": "Victoria, Mahé, Seychelles",
      "time_in_port": "7am-6pm",
      "top_activity": "La Digue island excursion with Anse Source d'Argent (€129)",
      "tip": "Book tender tickets early; bring reef shoes for granite beach access"
    },
    {
      "port": "Colombo, Sri Lanka",
      "time_in_port": "8am-8pm (overnight on some sailings)",
      "top_activity": "Sigiriya Rock Fortress day trip (€189)",
      "tip": "Overnight stay allows independent Galle Face Hotel sundowner experience"
    },
    {
      "port": "Pointe des Galets, Réunion",
      "time_in_port": "8am-6pm",
      "top_activity": "Piton de la Fournaise volcano and cirque of Salazie (€119)",
      "tip": "French territory uses euros; excellent for self-drive scenic routes"
    },
    {
      "port": "Malé, Maldives",
      "time_in_port": "7am-5pm",
      "top_activity": "Resort island day pass with overwater lunch (€159)",
      "tip": "Independent dhoni boat to local islands costs fraction of ship excursions"
    },
    {
      "port": "Mumbai, India",
      "time_in_port": "8am-8pm",
      "top_activity": "Elephanta Caves and colonial heritage walking tour (€79)",
      "tip": "Pre-arrange guide for Gateway of India area; intense traffic requires patience"
    }
  ],
  "faqs": [
    {
      "question": "How much does a P&O Cruises Indian Ocean cruise cost?",
      "answer": "P&O Indian Ocean cruises typically range from €1,699 to €4,599 per person for 14-35 night itineraries. Inside cabins start around €1,899 in shoulder season, rising to €2,199 peak months. Balcony accommodations, essential for enjoying equatorial sunsets and ocean vistas, command €2,499-€2,899. Suites with butler service begin at €3,299. Fly-cruise packages from regional UK airports add approximately €400-600. All fares include meals, entertainment, and gratuities. Select Price fares offer cabin choice and onboard credit, while Saver Prices provide lowest rates with assigned accommodation. Solo travellers should note P&O's single supplements range 40-100%, though dedicated single cabins on Arcadia and Aurora offer better value."
    },
    {
      "question": "Which P&O Cruises ships sail to Indian Ocean?",
      "answer": "Four P&O vessels operate Indian Ocean routes, each offering distinct experiences. Arcadia, adults-only with 2,096 guests, provides the most intimate sophisticated atmosphere with extensive spa facilities. Aurora, similarly adults-only and smaller at 1,870 capacity, specialises in world voyage segments with enriched programming. Azura and Ventura accommodate families with 3,100 and 3,092 guests respectively, featuring expansive kids' clubs, waterslides, and family entertainment. Arcadia and Aurora dominate winter 2025-2026 Indian Ocean deployment with dedicated 14-18 night fly-cruises from Valletta and Dubai. Ventura offers occasional grand voyages from Southampton. Ship choice depends entirely on whether you prioritise child-free tranquillity or multi-generational facilities."
    },
    {
      "question": "When is best time to cruise Indian Ocean?",
      "answer": "Optimal Indian Ocean cruising occurs November through March when northeast monsoons deliver dry, sunny conditions with temperatures 26-32°C and minimal rainfall. December to February represents absolute peak, particularly for Maldives and Seychelles where water visibility exceeds 30 metres for exceptional snorkelling. Mauritius and Réunion enjoy their summer with warmest seas ideal for swimming. April and October offer shoulder season value with occasional showers but pleasant conditions. May through September brings southeast trade winds, cooler temperatures, and rougher seas—avoidable for comfort though South Africa positioning cruises still operate. Cyclone risk in Mauritius and Réunion peaks January-March but remains statistically low; ships adjust itineraries if necessary."
    },
    {
      "question": "What is included?",
      "answer": "P&O's Indian Ocean cruises include comprehensive value: all meals across main dining rooms, buffet venues, and daytime grills; afternoon tea with sandwiches and pastries; evening entertainment from West End-style productions to live music; supervised children's clubs for ages 2-17; fitness centre, pools, and sports courts; port taxes and automatic gratuities; British pound currency eliminating exchange complications; enrichment lectures on destination culture and history; and shuttle buses in most ports. Accommodation steward service maintains cabins twice daily. Notable inclusions distinguishing P&O include formal nights with complimentary champagne receptions and dedicated single cabins without punitive supplements. Beverages, speciality dining, spa services, WiFi, and organised excursions incur additional charges."
    },
    {
      "question": "Which ports?",
      "answer": "P&O's Indian Ocean itineraries encompass diverse destinations across three sub-regions. East African calls include Port Louis (Mauritius) for French-Creole culture and tea plantations, Victoria (Mahé) for Seychelles' granite beaches and giant tortoises, and Pointe des Galets (Réunion) for dramatic volcanic landscapes. Indian subcontinent features Mumbai for colonial architecture and Bollywood energy, Colombo for Buddhist heritage and tea country access, and occasional Kochi calls. Arabian Peninsula extensions incorporate Muscat's souks and forts, Dubai's modern opulence, and Aqaba for Petra access. Extended voyages reach Durban and Cape Town for South African wildlife. Most itineraries offer 8-12 hour port stays with occasional overnights in Colombo and Port Louis enabling independent evening exploration."
    },
    {
      "question": "How far ahead to book?",
      "answer": "Secure P&O Indian Ocean cruises 12-18 months ahead for optimal results, particularly when seeking specific cabin categories like aft-facing balconies or single accommodations with limited inventory. Early booking discounts of 25-35% apply to reservations made 18+ months pre-departure. Balcony cabins on adults-only Arcadia sell fastest for winter sun departures. P&O releases itineraries approximately two years ahead, with priority booking windows for Peninsular Club loyalty members. Last-minute deals emerge 8-12 weeks before sailing for flexible travellers, though cabin location and dining preferences may be compromised. Deposit structures require 15% at booking, fully refundable until 90 days before departure for Select Price fares. Consider booking flights independently for better schedules and pricing."
    },
    {
      "question": "Good for families?",
      "answer": "P&O Indian Ocean cruises suit families exceptionally through Azura and Ventura's comprehensive facilities, though parents should weigh extended sea days against children's patience. Kids' clubs operate 9am-midnight with age-appropriate programming: Splashers (2-4), Surfers (5-8), Scubas (9-12), and H2O (13-17). Night Nursery provides complimentary babysitting 6pm-2am for under-fives. Family pools, cinemas, and sports courts entertain sea days between exotic ports. However, Indian Ocean itineraries feature numerous sea days—some exceeding three consecutive—challenging younger children. Shore excursions emphasise cultural and natural experiences less suited to toddlers. Family balcony cabins and interconnecting rooms accommodate groups, but P&O's traditional atmosphere with formal nights and structured dining may contrast with casual family preferences. Arcadia and Aurora remain adults-only."
    },
    {
      "question": "Cancellation policy?",
      "answer": "P&O's cancellation structure operates on a sliding scale based on departure proximity. Cancellations 91+ days before sailing incur loss of deposit only (typically 15% of cruise fare). 90-61 days forfeits 25% of total fare; 60-42 days loses 50%; 41-28 days sacrifices 75%; and 27 days or less results in 100% forfeiture. Travel insurance with cancellation coverage is strongly recommended given these penalties. P&O offers Cruise Cover protection at booking providing full refund for covered reasons including illness and redundancy. COVID-19 flexibility policies have been largely discontinued, reverting to standard terms. Name changes incur €75 administration fees if completed 14+ days before departure. Rebooking to alternative sailings within 12 months may be permitted with fare adjustments, subject to availability and administrative charges."
    }
  ]
}